filux_framework/__init__.py
filux_framework/io/Directory.py
filux_framework/io/File.py
filux_framework/io/Path.py
filux_framework/io/file_types/ImageFile.py
filux_framework/io/file_types/TextFile.py
filux_framework/system/Cache.py
filux_framework/system/Download.py
filux_framework/system/DuplicateFinder.py
filux_framework-0.2.1.dist-info/licenses/LICENSE.txt
filux_framework-0.2.1.dist-info/METADATA
filux_framework-0.2.1.dist-info/WHEEL
filux_framework-0.2.1.dist-info/top_level.txt
filux_framework-0.2.1.dist-info/RECORD
