Metadata-Version: 2.4
Name: filux-framework
Version: 0.2.1
Summary: A Python File Framework
Author: Blonicx
License: 
Requires-Python: >=3.8
License-File: LICENSE.txt
Requires-Dist: Pillow
Dynamic: license-file
